pycrypt.so
pycrypt-0.7.2.dist-info/DESCRIPTION.rst
pycrypt-0.7.2.dist-info/METADATA
pycrypt-0.7.2.dist-info/RECORD
pycrypt-0.7.2.dist-info/WHEEL
pycrypt-0.7.2.dist-info/metadata.json
pycrypt-0.7.2.dist-info/top_level.txt
