Metadata-Version: 1.1
Name: pycrypt
Version: 0.7.2
Summary: Fast TwoFish encryption.
Home-page: https://github.com/Noctem/pycrypt
Author: David Christenson
Author-email: mail@noctem.xyz
License: MIT
Keywords: pycrypt twofish pogo encryption cython
Platform: UNKNOWN
Classifier: Development Status :: 4 - Beta
Classifier: Intended Audience :: Developers
Classifier: Programming Language :: Cython
Classifier: Programming Language :: Python :: 2
Classifier: Programming Language :: Python :: 2.7
Classifier: Programming Language :: Python :: 3
Classifier: Programming Language :: Python :: 3.3
Classifier: Programming Language :: Python :: 3.4
Classifier: Programming Language :: Python :: 3.5
Classifier: Programming Language :: Python :: 3.6
Classifier: Topic :: Security :: Cryptography
Classifier: License :: OSI Approved :: MIT License
